setup.py
model_cache/__init__.py
model_cache/model_cache.py
model_cache/model_cache_class.py
model_cache.egg-info/PKG-INFO
model_cache.egg-info/SOURCES.txt
model_cache.egg-info/dependency_links.txt
model_cache.egg-info/not-zip-safe
model_cache.egg-info/pbr.json
model_cache.egg-info/requires.txt
model_cache.egg-info/top_level.txt
model_cache/storage/__init__.py
model_cache/storage/_base.py
model_cache/storage/memory_cache_store_memory.py
model_cache/storage/memory_cache_store_redis.py
model_cache/storage/memory_cache_store_shelve.py
model_cache/storage/memory_cache_store_sqlite.py
model_cache/tests/__init__.py
model_cache/tests/share.py
model_cache/tools/__init__.py
model_cache/tools/parallel.py