Metadata-Version: 1.1
Name: model-cache
Version: 0.1.1
Summary: model_cache
Home-page: http://github.com/17zuoye/model_cache/
Author: David Chen
Author-email: mvjome@gmail.com
License: MIT
Platform: any
Classifier: Intended Audience :: Developers
Classifier: Operating System :: OS Independent
Classifier: Programming Language :: Python
Classifier: Topic :: Software Development :: Libraries :: Python Modules
